mlfz/__init__.py
mlfz/datasets.py
mlfz/scores.py
mlfz/classical/__init__.py
mlfz/classical/base.py
mlfz/classical/knn.py
mlfz/classical/linear.py
mlfz/classical/pca.py
mlfz/classical/pipeline.py
mlfz/classical/scaler.py
mlfz/classical/tree/__init__.py
mlfz/classical/tree/cart.py
mlfz/functional/__init__.py
mlfz/functional/numpy.py
mlfz/functional/vanilla.py
mlfz/nn/__init__.py
mlfz/nn/model.py
mlfz/nn/scalar/__init__.py
mlfz/nn/scalar/core.py
mlfz/nn/scalar/functional.py
mlfz/nn/scalar/loss.py
mlfz/nn/scalar/optimizer.py
mlfz/nn/tensor/__init__.py
mlfz/nn/tensor/functional.py
mlfz/nn/tensor/loss.py
mlfz/nn/tensor/core/__init__.py
mlfz/nn/tensor/core/tensor.py
mlfz/nn/tensor/core/utils.py
mlfz-0.1.3.3.dist-info/licenses/LICENSE
mlfz-0.1.3.3.dist-info/METADATA
mlfz-0.1.3.3.dist-info/WHEEL
mlfz-0.1.3.3.dist-info/top_level.txt
mlfz-0.1.3.3.dist-info/RECORD
