Metadata-Version: 2.4
Name: mlfz
Version: 0.1.3.3
Summary: Machine Learning From Zero: an educational machine learning library.
Home-page: https://github.com/cosmic-cortex/mlfz
Author: Tivadar Danka
Classifier: Programming Language :: Python :: 3
Classifier: License :: OSI Approved :: MIT License
Classifier: Operating System :: OS Independent
Requires-Python: >=3.10
License-File: LICENSE
Dynamic: author
Dynamic: classifier
Dynamic: description
Dynamic: description-content-type
Dynamic: home-page
Dynamic: license-file
Dynamic: requires-python
Dynamic: summary
